setup.py
djangotoapk/__init__.py
djangotoapk/apps.py
djangotoapk/urls.py
djangotoapk/views.py
djangotoapk.egg-info/PKG-INFO
djangotoapk.egg-info/SOURCES.txt
djangotoapk.egg-info/dependency_links.txt
djangotoapk.egg-info/requires.txt
djangotoapk.egg-info/top_level.txt