Metadata-Version: 1.1
Name: djangotoapk
Version: 0.2
Summary: Deploy Django web application on Android as APK.
Home-page: http://yeisoncardona.com/
Author: Yeison Cardona
Author-email: yeisoneng@gmail.com
License: BSD License
Download-URL: https://bitbucket.org/djangoforandroid/djangotoapk/downloads
Platform: UNKNOWN
Classifier: Environment :: Web Environment
Classifier: Framework :: Django
